docassemble/demo/__init__.py
docassemble/demo/accordion.py
docassemble/demo/alembic.ini
docassemble/demo/attorney.py
docassemble/demo/calendar.py
docassemble/demo/cards.py
docassemble/demo/change_suffix.py
docassemble/demo/chatbot.py
docassemble/demo/chatbot_bg.py
docassemble/demo/chatbot_bg_object.py
docassemble/demo/companydb.py
docassemble/demo/contexttest.py
docassemble/demo/custombg.py
docassemble/demo/demodb.py
docassemble/demo/ein.py
docassemble/demo/fish.py
docassemble/demo/fishlist.py
docassemble/demo/fonts.py
docassemble/demo/fruit_database.py
docassemble/demo/gd_fetch.py
docassemble/demo/gettime.py
docassemble/demo/google_drive.py
docassemble/demo/google_sheets.py
docassemble/demo/google_vision2.py
docassemble/demo/graph.py
docassemble/demo/hello.py
docassemble/demo/income.py
docassemble/demo/index.py
docassemble/demo/interrelated.py
docassemble/demo/legume.py
docassemble/demo/oauthsheets.py
docassemble/demo/objects.py
docassemble/demo/progressivedisclosure.py
docassemble/demo/random-test.py
docassemble/demo/read_snapshot.py
docassemble/demo/reldemodb.py
docassemble/demo/sign.py
docassemble/demo/somefuncs.py
docassemble/demo/ssn.py
docassemble/demo/testcontexttest.py
docassemble/demo/testcustombg.py
docassemble/demo/tests.py
docassemble/demo/translate.py
docassemble/demo/user_permissions.py
docassemble/demo/validationfuncs.py
docassemble/demo/validationfuncstwo.py
docassemble/demo/alembic/README
docassemble/demo/alembic/env.py
docassemble/demo/alembic/script.py.mako
docassemble/demo/data/objects/organizations.yml
docassemble/demo/data/questions/animal.yml
docassemble/demo/data/questions/conflict_check.yml
docassemble/demo/data/questions/demo-basic-questions-address.yml
docassemble/demo/data/questions/demo-basic-questions-name.yml
docassemble/demo/data/questions/demo-basic-questions.yml
docassemble/demo/data/questions/event-role-event.yml
docassemble/demo/data/questions/fontlist.yml
docassemble/demo/data/questions/hello.yml
docassemble_demo-1.9.0.dist-info/licenses/LICENSE.txt
docassemble_demo-1.9.0.dist-info/METADATA
docassemble_demo-1.9.0.dist-info/WHEEL
docassemble_demo-1.9.0.dist-info/top_level.txt
docassemble_demo-1.9.0.dist-info/RECORD
