Metadata-Version: 2.4
Name: docassemble.demo
Version: 1.9.0
Summary: A demonstration package for docassemble.
Author-email: Jonathan Pyle <jhpyle@gmail.com>
License-Expression: MIT
Project-URL: Homepage, https://docassemble.org
Project-URL: Documentation, https://docassemble.org/docs.html
Project-URL: Repository, https://github.com/jhpyle/docassemble.git
Project-URL: Bug Tracker, https://github.com/jhpyle/docassemble/issues
Project-URL: Changelog, https://github.com/jhpyle/docassemble/blob/master/CHANGELOG.md
Requires-Python: >=3.9
License-File: LICENSE.txt
Requires-Dist: docassemble.base==1.9.0
Requires-Dist: googledrivedownloader
Requires-Dist: ics
Requires-Dist: matplotlib
Dynamic: license-file
